computer_talk/__init__.py
computer_talk/cli.py
computer_talk/config.py
computer_talk/core.py
computer_talk/desktop.py
computer_talk/exceptions.py
computer_talk/first_run.py
computer_talk-0.1.12.dist-info/licenses/LICENSE
computer_talk-0.1.12.dist-info/METADATA
computer_talk-0.1.12.dist-info/WHEEL
computer_talk-0.1.12.dist-info/entry_points.txt
computer_talk-0.1.12.dist-info/top_level.txt
computer_talk-0.1.12.dist-info/RECORD
